[
  {
    "slug": "score-reform-2025",
    "title": "2025年中考改革与510分制说明",
    "description": "解读2025年北京中考总分由670分调整为510分的变化，以及如何正确比较历年分数线。",
    "date": "2026-04-07",
    "category": "政策概览",
    "readingMinutes": 2
  },
  {
    "slug": "guantong-project",
    "title": "贯通培养项目报考指南",
    "description": "贯通培养项目是北京中考提前招生的重要组成部分，提供7年一贯制培养模式。",
    "date": "2026-04-06",
    "category": "提前招生",
    "readingMinutes": 3
  },
  {
    "slug": "special-candidates",
    "title": "回户籍与往届生报考限制说明",
    "description": "详解回户籍考生和往届生在北京中考中的报考限制和注意事项。",
    "date": "2026-04-05",
    "category": "报考资格",
    "readingMinutes": 2
  },
  {
    "slug": "comprehensive-evaluation",
    "title": "综合素质评价说明",
    "description": "综合素质评价是北京中考的重要环节，直接影响指标分配招生的填报资格。",
    "date": "2026-04-04",
    "category": "综合评价",
    "readingMinutes": 2
  },
  {
    "slug": "unified-admission-tips",
    "title": "统一招生志愿填报技巧",
    "description": "统一招生是大多数考生的主要录取渠道，掌握填报技巧至关重要。",
    "date": "2026-04-03",
    "category": "志愿填报",
    "readingMinutes": 2
  },
  {
    "slug": "quota-admission-guide",
    "title": "指标分配招生填报指南",
    "description": "指标分配招生包括校额到校和市级统筹，本文详细说明填报流程和注意事项。",
    "date": "2026-04-02",
    "category": "指标分配",
    "readingMinutes": 2
  },
  {
    "slug": "xiao-e-dao-xiao",
    "title": "校额到校政策完全解读",
    "description": "详解北京中考校额到校招生政策，包括资格条件、填报方法和录取规则。",
    "date": "2026-04-01",
    "category": "指标分配",
    "readingMinutes": 2
  },
  {
    "slug": "2026-policy-overview",
    "title": "2026年北京中招政策概览",
    "description": "全面解读2026年北京市高级中等学校考试招生工作的核心政策变化与要点。",
    "date": "2026-03-30",
    "category": "政策概览",
    "readingMinutes": 2
  }
]
